<?xml version="1.0" encoding="utf-8"?>
<resources>
    <string-array name="listi">
        <item>iberia</item>
        <item>iberian</item>
        <item>ibiza</item>
        <item>ice</item>
        <item>iceberg</item>
        <item>icebox</item>
        <item>iceland</item>
        <item>icelandic</item>
        <item>icicle</item>
        <item>icon</item>
        <item>iconic</item>
        <item>icy</item>
        <item>idea</item>
        <item>ideal</item>
        <item>idealism</item>
        <item>idealist</item>
        <item>idealistic</item>
        <item>ideally</item>
        <item>identification</item>
        <item>identical</item>
        <item>identifier</item>
        <item>identify</item>
        <item>identity</item>
        <item>ideological</item>
        <item>ideologist</item>
        <item>ideology</item>
        <item>idiocy</item>
        <item>idiom</item>
        <item>idiomatic</item>
        <item>idiot</item>
        <item>idiotic</item>
        <item>idle</item>
        <item>idleness</item>
        <item>idler</item>
        <item>idol</item>
        <item>idolater</item>
        <item>idolize</item>
        <item>idyll</item>
        <item>idyllic</item>
        <item>iffy</item>
        <item>ignite</item>
        <item>ignition</item>
        <item>ignorance</item>
        <item>ignorant</item>
        <item>ignore</item>
        <item>ill</item>
        <item>illegal</item>
        <item>illegality</item>
        <item>illegitimacy</item>
        <item>illegitimate</item>
        <item>illicit</item>
        <item>illinois</item>
        <item>illinoisan</item>
        <item>illiteracy</item>
        <item>illiterate</item>
        <item>illness</item>
        <item>illogical</item>
        <item>illogicality</item>
        <item>illuminable</item>
        <item>illumination</item>
        <item>illumine</item>
        <item>illusion</item>
        <item>illusionary</item>
        <item>illusionist</item>
        <item>illusive</item>
        <item>illusory</item>
        <item>illustrate</item>
        <item>illustration</item>
        <item>illustrational</item>
        <item>illustrative</item>
        <item>illustrator</item>
        <item>image</item>
        <item>imagery</item>
        <item>imaginable</item>
        <item>imaginary</item>
        <item>imagination</item>
        <item>imaginative</item>
        <item>imagine</item>
        <item>imbalance</item>
        <item>imbecile</item>
        <item>imbecility</item>
        <item>imitable</item>
        <item>imitate</item>
        <item>imitation</item>
        <item>imitative</item>
        <item>immaculate</item>
        <item>immature</item>
        <item>immaturity</item>
        <item>immeasurable</item>
        <item>immediacy</item>
        <item>immediate</item>
        <item>immediately</item>
        <item>immemorial</item>
        <item>immense</item>
        <item>immensity</item>
        <item>immensurable</item>
        <item>immerse</item>
        <item>immersion</item>
        <item>immersive</item>
        <item>immigrant</item>
        <item>immigrate</item>
        <item>immigration</item>
        <item>imminence</item>
        <item>imminent</item>
        <item>immobility</item>
        <item>immoral</item>
        <item>immorality</item>
        <item>immortal</item>
        <item>immortality</item>
        <item>immortalize</item>
        <item>immovable</item>
        <item>immune</item>
        <item>immunity</item>
        <item>immunization</item>
        <item>immunize</item>
        <item>impact</item>
        <item>impactful</item>
        <item>impair</item>
        <item>impairment</item>
        <item>impala</item>
        <item>imparity</item>
        <item>impartial</item>
        <item>impatience</item>
        <item>impatient</item>
        <item>impeach</item>
        <item>impeachable</item>
        <item>impeachment</item>
        <item>impeccable</item>
        <item>impedance</item>
        <item>impede</item>
        <item>impediment</item>
        <item>impenetrability</item>
        <item>impenetrable</item>
        <item>imperative</item>
        <item>imperfect</item>
        <item>imperfection</item>
        <item>imperial</item>
        <item>imperialism</item>
        <item>imperishable</item>
        <item>impermanent</item>
        <item>impermeable</item>
        <item>impersonal</item>
        <item>impersonalism</item>
        <item>impersonate</item>
        <item>impersonator</item>
        <item>impertinence</item>
        <item>impertinent</item>
        <item>impiety</item>
        <item>impious</item>
        <item>implant</item>
        <item>implantable</item>
        <item>implantation</item>
        <item>implement</item>
        <item>implementation</item>
        <item>implicate</item>
        <item>implication</item>
        <item>implicit</item>
        <item>implode</item>
        <item>implore</item>
        <item>implosion</item>
        <item>imply</item>
        <item>impolite</item>
        <item>import</item>
        <item>importance</item>
        <item>important</item>
        <item>impose</item>
        <item>impossibility</item>
        <item>impossible</item>
        <item>impostor</item>
        <item>imposture</item>
        <item>impotence</item>
        <item>impractical</item>
        <item>imprecise</item>
        <item>impregnate</item>
        <item>impress</item>
        <item>impressible</item>
        <item>impression</item>
        <item>impressionist</item>
        <item>impressive</item>
        <item>imprison</item>
        <item>improbable</item>
        <item>improbability</item>
        <item>improper</item>
        <item>improve</item>
        <item>improvement</item>
        <item>improvisatory</item>
        <item>improvise</item>
        <item>impudence</item>
        <item>impudent</item>
        <item>impulse</item>
        <item>impulsion</item>
        <item>impulsive</item>
        <item>impunity</item>
        <item>impure</item>
        <item>impurity</item>
        <item>inability</item>
        <item>inaccessible</item>
        <item>inaccuracy</item>
        <item>inaccurate</item>
        <item>inaction</item>
        <item>inactive</item>
        <item>inadequacy</item>
        <item>inadequate</item>
        <item>inadmissible</item>
        <item>inalienable</item>
        <item>inanimate</item>
        <item>inapplicable</item>
        <item>inapproachable</item>
        <item>inappropriate</item>
        <item>inapt</item>
        <item>inaptitude</item>
        <item>inattention</item>
        <item>inattentive</item>
        <item>inaudible</item>
        <item>inaugurate</item>
        <item>inauguration</item>
        <item>inauspicious</item>
        <item>inbred</item>
        <item>inbreed</item>
        <item>incandescence</item>
        <item>incandescent</item>
        <item>incantation</item>
        <item>incapable</item>
        <item>incapacitate</item>
        <item>incapacity</item>
        <item>incarcerate</item>
        <item>incarceration</item>
        <item>incarnate</item>
        <item>incarnation</item>
        <item>incendiary</item>
        <item>incense</item>
        <item>incentive</item>
        <item>inception</item>
        <item>incertitude</item>
        <item>incest</item>
        <item>inch</item>
        <item>incidence</item>
        <item>incident</item>
        <item>incidental</item>
        <item>incidentally</item>
        <item>incinerate</item>
        <item>incinerator</item>
        <item>incision</item>
        <item>incite</item>
        <item>incitement</item>
        <item>inclination</item>
        <item>inclinatory</item>
        <item>incline</item>
        <item>include</item>
        <item>inclusion</item>
        <item>inclusive</item>
        <item>incognito</item>
        <item>incoherence</item>
        <item>incoherent</item>
        <item>income</item>
        <item>incommensurable</item>
        <item>incommode</item>
        <item>incomparable</item>
        <item>incompetence</item>
        <item>incompetent</item>
        <item>incomplete</item>
        <item>incomprehensible</item>
        <item>incomprehensive</item>
        <item>incompressible</item>
        <item>inconceivable</item>
        <item>inconsequent</item>
        <item>inconsiderable</item>
        <item>inconsiderate</item>
        <item>inconsistency</item>
        <item>inconsistent</item>
        <item>inconvenience</item>
        <item>inconveniency</item>
        <item>inconvenient</item>
        <item>incorporate</item>
        <item>incorporation</item>
        <item>incorrect</item>
        <item>increase</item>
        <item>incredible</item>
        <item>increment</item>
        <item>incremental</item>
        <item>incriminate</item>
        <item>incubate</item>
        <item>incubation</item>
        <item>incubator</item>
        <item>inculpable</item>
        <item>inculpate</item>
        <item>incursion</item>
        <item>indecency</item>
        <item>indecent</item>
        <item>indecision</item>
        <item>indecisive</item>
        <item>indeed</item>
        <item>indefinable</item>
        <item>indefinite</item>
        <item>indefinitely</item>
        <item>indent</item>
        <item>indentation</item>
        <item>independence</item>
        <item>independent</item>
        <item>indescribable</item>
        <item>indestructible</item>
        <item>indeterminable</item>
        <item>indeterminacy</item>
        <item>indeterminate</item>
        <item>index</item>
        <item>india</item>
        <item>indian</item>
        <item>indiana</item>
        <item>indicate</item>
        <item>indication</item>
        <item>indicator</item>
        <item>indicative</item>
        <item>indices</item>
        <item>indifference</item>
        <item>indifferent</item>
        <item>indigenous</item>
        <item>indigestible</item>
        <item>indigestion</item>
        <item>indigo</item>
        <item>indirect</item>
        <item>indiscreet</item>
        <item>indiscretion</item>
        <item>indiscriminate</item>
        <item>individual</item>
        <item>individually</item>
        <item>indivisible</item>
        <item>indolence</item>
        <item>indolent</item>
        <item>indonesia</item>
        <item>indonesian</item>
        <item>indoor</item>
        <item>indoors</item>
        <item>induce</item>
        <item>induct</item>
        <item>induction</item>
        <item>indulge</item>
        <item>indulgence</item>
        <item>indulgent</item>
        <item>industrial</item>
        <item>industrialism</item>
        <item>industrialist</item>
        <item>industrialization</item>
        <item>industrialize</item>
        <item>industry</item>
        <item>ineffective</item>
        <item>inefficacy</item>
        <item>inefficient</item>
        <item>inelastic</item>
        <item>ineligible</item>
        <item>inept</item>
        <item>inequality</item>
        <item>inequitable</item>
        <item>inequity</item>
        <item>inert</item>
        <item>inertia</item>
        <item>inertial</item>
        <item>inescapable</item>
        <item>inessential</item>
        <item>inevitable</item>
        <item>inexcusable</item>
        <item>inexhaustible</item>
        <item>inexpensive</item>
        <item>inexperience</item>
        <item>inextensible</item>
        <item>infallibility</item>
        <item>infallible</item>
        <item>infamous</item>
        <item>infamy</item>
        <item>infancy</item>
        <item>infant</item>
        <item>infantile</item>
        <item>infantry</item>
        <item>infantryman</item>
        <item>infatuate</item>
        <item>infatuation</item>
        <item>infect</item>
        <item>infection</item>
        <item>infectious</item>
        <item>infective</item>
        <item>infelicitous</item>
        <item>infelicity</item>
        <item>infer</item>
        <item>inferential</item>
        <item>inferior</item>
        <item>infernal</item>
        <item>inferno</item>
        <item>infertile</item>
        <item>infertility</item>
        <item>infest</item>
        <item>infestation</item>
        <item>infidel</item>
        <item>infidelity</item>
        <item>infiltrate</item>
        <item>infiltration</item>
        <item>infinite</item>
        <item>infinitesimal</item>
        <item>infinitive</item>
        <item>infinity</item>
        <item>infirmary</item>
        <item>inflame</item>
        <item>inflammable</item>
        <item>inflammation</item>
        <item>inflammatory</item>
        <item>inflate</item>
        <item>inflation</item>
        <item>inflationary</item>
        <item>inflect</item>
        <item>inflection</item>
        <item>inflict</item>
        <item>infliction</item>
        <item>influence</item>
        <item>influencer</item>
        <item>influential</item>
        <item>info</item>
        <item>inform</item>
        <item>informal</item>
        <item>informality</item>
        <item>informatics</item>
        <item>information</item>
        <item>informative</item>
        <item>informatory</item>
        <item>informer</item>
        <item>infra</item>
        <item>infrared</item>
        <item>infrastructure</item>
        <item>infrequency</item>
        <item>infrequent</item>
        <item>infringe</item>
        <item>infringement</item>
        <item>infuriate</item>
        <item>infuse</item>
        <item>infusion</item>
        <item>ingenious</item>
        <item>ingenuity</item>
        <item>ingenuous</item>
        <item>ingest</item>
        <item>ingestion</item>
        <item>ingot</item>
        <item>ingredient</item>
        <item>inhabit</item>
        <item>inhabitant</item>
        <item>inhalation</item>
        <item>inhalator</item>
        <item>inhale</item>
        <item>inharmonious</item>
        <item>inhere</item>
        <item>inherent</item>
        <item>inheritable</item>
        <item>inheritance</item>
        <item>inheritor</item>
        <item>inhibit</item>
        <item>inhibition</item>
        <item>inhibitor</item>
        <item>inhibitory</item>
        <item>inhuman</item>
        <item>inhumane</item>
        <item>initial</item>
        <item>initialize</item>
        <item>initiate</item>
        <item>initiation</item>
        <item>initiative</item>
        <item>initiator</item>
        <item>initiatory</item>
        <item>inject</item>
        <item>injection</item>
        <item>injunction</item>
        <item>injure</item>
        <item>injury</item>
        <item>injustice</item>
        <item>ink</item>
        <item>inlaid</item>
        <item>inland</item>
        <item>inline</item>
        <item>inmate</item>
        <item>innate</item>
        <item>inner</item>
        <item>innermost</item>
        <item>innocence</item>
        <item>innocent</item>
        <item>innovate</item>
        <item>innovation</item>
        <item>innumerable</item>
        <item>inoffensive</item>
        <item>inopportune</item>
        <item>inorganic</item>
        <item>inpatient</item>
        <item>input</item>
        <item>inquire</item>
        <item>inquiry</item>
        <item>inquisition</item>
        <item>inquisitive</item>
        <item>insane</item>
        <item>insanity</item>
        <item>insanitary</item>
        <item>insatiable</item>
        <item>inscription</item>
        <item>insect</item>
        <item>insecticide</item>
        <item>insecure</item>
        <item>insecurity</item>
        <item>inseminate</item>
        <item>insemination</item>
        <item>insensible</item>
        <item>insensitive</item>
        <item>inseparable</item>
        <item>insert</item>
        <item>insertion</item>
        <item>inshore</item>
        <item>inside</item>
        <item>insider</item>
        <item>insight</item>
        <item>insightful</item>
        <item>insignificance</item>
        <item>insignificant</item>
        <item>insinuate</item>
        <item>insinuation</item>
        <item>insipid</item>
        <item>insist</item>
        <item>insistence</item>
        <item>insistent</item>
        <item>insolence</item>
        <item>insolent</item>
        <item>insoluble</item>
        <item>insolvable</item>
        <item>insolvency</item>
        <item>insolvent</item>
        <item>insomnia</item>
        <item>insomniac</item>
        <item>inspect</item>
        <item>inspection</item>
        <item>inspector</item>
        <item>inspiration</item>
        <item>inspirational</item>
        <item>inspire</item>
        <item>instability</item>
        <item>instable</item>
        <item>install</item>
        <item>installation</item>
        <item>installment</item>
        <item>instance</item>
        <item>instant</item>
        <item>instantaneous</item>
        <item>instantiate</item>
        <item>instantly</item>
        <item>instead</item>
        <item>instigate</item>
        <item>instigation</item>
        <item>instinct</item>
        <item>instinctive</item>
        <item>institute</item>
        <item>institution</item>
        <item>institutional</item>
        <item>instruct</item>
        <item>instruction</item>
        <item>instructions</item>
        <item>instructive</item>
        <item>instrument</item>
        <item>instrumental</item>
        <item>instrumentation</item>
        <item>insubordinate</item>
        <item>insubordination</item>
        <item>insufficiency</item>
        <item>insufficient</item>
        <item>insular</item>
        <item>insulate</item>
        <item>insulation</item>
        <item>insulin</item>
        <item>insult</item>
        <item>insupportable</item>
        <item>insurance</item>
        <item>insure</item>
        <item>insurgence</item>
        <item>insurgency</item>
        <item>insurgent</item>
        <item>insurmountable</item>
        <item>intact</item>
        <item>intake</item>
        <item>intangible</item>
        <item>integer</item>
        <item>integrable</item>
        <item>integral</item>
        <item>integrate</item>
        <item>integration</item>
        <item>intellect</item>
        <item>intellectual</item>
        <item>intellectuality</item>
        <item>intellectualize</item>
        <item>intelligence</item>
        <item>intelligent</item>
        <item>intelligible</item>
        <item>intend</item>
        <item>intense</item>
        <item>intensifier</item>
        <item>intensify</item>
        <item>intensity</item>
        <item>intensive</item>
        <item>intent</item>
        <item>intention</item>
        <item>intentional</item>
        <item>interact</item>
        <item>interaction</item>
        <item>interactive</item>
        <item>intercept</item>
        <item>interception</item>
        <item>interceptor</item>
        <item>interchange</item>
        <item>interchangeable</item>
        <item>intercom</item>
        <item>intercommunicate</item>
        <item>interconnect</item>
        <item>intercontinental</item>
        <item>intercourse</item>
        <item>interdependence</item>
        <item>interdependent</item>
        <item>interdict</item>
        <item>interdiction</item>
        <item>interdisciplinary</item>
        <item>interest</item>
        <item>interface</item>
        <item>interfere</item>
        <item>interference</item>
        <item>intergalactic</item>
        <item>interim</item>
        <item>interior</item>
        <item>interlace</item>
        <item>interlock</item>
        <item>interlope</item>
        <item>interlude</item>
        <item>intermediary</item>
        <item>intermediate</item>
        <item>intermittent</item>
        <item>intern</item>
        <item>internal</item>
        <item>international</item>
        <item>internet</item>
        <item>internship</item>
        <item>interpersonal</item>
        <item>interpolate</item>
        <item>interpolation</item>
        <item>interpose</item>
        <item>interposition</item>
        <item>interpret</item>
        <item>interpretation</item>
        <item>interpreter</item>
        <item>interpretive</item>
        <item>interracial</item>
        <item>interrogate</item>
        <item>interrogation</item>
        <item>interrogative</item>
        <item>interrogator</item>
        <item>interrupt</item>
        <item>interruption</item>
        <item>intersect</item>
        <item>intersection</item>
        <item>interstate</item>
        <item>interstitial</item>
        <item>interval</item>
        <item>intervene</item>
        <item>intervention</item>
        <item>interview</item>
        <item>interviewee</item>
        <item>interviewer</item>
        <item>intestinal</item>
        <item>intestine</item>
        <item>intestines</item>
        <item>intimacy</item>
        <item>intimate</item>
        <item>intimidate</item>
        <item>into</item>
        <item>intolerable</item>
        <item>intolerance</item>
        <item>intolerant</item>
        <item>intonation</item>
        <item>intone</item>
        <item>intoxicant</item>
        <item>intoxicate</item>
        <item>intoxication</item>
        <item>intracellular</item>
        <item>intransigence</item>
        <item>intransigent</item>
        <item>intrapersonal</item>
        <item>intricacy</item>
        <item>intricate</item>
        <item>intrigue</item>
        <item>intrinsic</item>
        <item>intro</item>
        <item>introduce</item>
        <item>introduction</item>
        <item>introductory</item>
        <item>introspect</item>
        <item>introspection</item>
        <item>introspective</item>
        <item>introversion</item>
        <item>introvert</item>
        <item>intrude</item>
        <item>intruder</item>
        <item>intrusion</item>
        <item>intrusive</item>
        <item>intuit</item>
        <item>intuition</item>
        <item>intuitive</item>
        <item>inundate</item>
        <item>invade</item>
        <item>invalid</item>
        <item>invalidity</item>
        <item>invalidate</item>
        <item>invaluable</item>
        <item>invariable</item>
        <item>invariant</item>
        <item>invasion</item>
        <item>invent</item>
        <item>invention</item>
        <item>inventive</item>
        <item>inventor</item>
        <item>inventory</item>
        <item>inverse</item>
        <item>inversion</item>
        <item>invert</item>
        <item>invertebrate</item>
        <item>invertebrates</item>
        <item>invest</item>
        <item>investigate</item>
        <item>investigation</item>
        <item>investigator</item>
        <item>investment</item>
        <item>invincible</item>
        <item>invisible</item>
        <item>invitation</item>
        <item>invite</item>
        <item>invoke</item>
        <item>invocation</item>
        <item>invoice</item>
        <item>involuntary</item>
        <item>involve</item>
        <item>invulnerable</item>
        <item>inward</item>
        <item>inwardly</item>
        <item>inwards</item>
        <item>iodine</item>
        <item>ion</item>
        <item>ionization</item>
        <item>ionize</item>
        <item>ionizer</item>
        <item>iowa</item>
        <item>iowan</item>
        <item>iran</item>
        <item>iranian</item>
        <item>iraq</item>
        <item>iraqi</item>
        <item>ireland</item>
        <item>iris</item>
        <item>irish</item>
        <item>iron</item>
        <item>ironic</item>
        <item>ironical</item>
        <item>ironically</item>
        <item>irony</item>
        <item>irradiate</item>
        <item>irradiation</item>
        <item>irrational</item>
        <item>irrationality</item>
        <item>irredeemable</item>
        <item>irregular</item>
        <item>irregularity</item>
        <item>irrelevance</item>
        <item>irrelevant</item>
        <item>irreligion</item>
        <item>irreligious</item>
        <item>irreplaceable</item>
        <item>irresistible</item>
        <item>irrespective</item>
        <item>irresponsible</item>
        <item>irreversible</item>
        <item>irrigate</item>
        <item>irrigation</item>
        <item>irritable</item>
        <item>irritant</item>
        <item>irritate</item>
        <item>irritation</item>
        <item>isaac</item>
        <item>islam</item>
        <item>island</item>
        <item>islands</item>
        <item>isle</item>
        <item>isolate</item>
        <item>isolation</item>
        <item>isosceles</item>
        <item>israel</item>
        <item>israeli</item>
        <item>issue</item>
        <item>istanbul</item>
        <item>italian</item>
        <item>italic</item>
        <item>italics</item>
        <item>italy</item>
        <item>itch</item>
        <item>itchy</item>
        <item>item</item>
        <item>itemize</item>
        <item>iterate</item>
        <item>iteration</item>
        <item>iterative</item>
        <item>itinerant</item>
        <item>itinerary</item>
        <item>its</item>
        <item>itself</item>
        <item>ivories</item>
        <item>ivory</item>
        <item>ivy</item>
    </string-array>
</resources>